MANIFEST.in
setup.py
gmailer_report/__init__.py
gmailer_report/postman.py
gmailer_report.egg-info/PKG-INFO
gmailer_report.egg-info/SOURCES.txt
gmailer_report.egg-info/dependency_links.txt
gmailer_report.egg-info/not-zip-safe
gmailer_report.egg-info/top_level.txt
gmailer_report/html_generator/__init__.py
gmailer_report/html_generator/generate_html.py
gmailer_report/html_generator/template/email.html
gmailer_report/html_generator/url_checker/__init__.py
gmailer_report/html_generator/url_checker/validator.py