Metadata-Version: 1.1
Name: gmailer-report
Version: 0.1a3
Summary: Gmailer_report simplifies the dispatch of standard html email reports that includes tabular data from Gmail.
Home-page: https://github.com/channeng/Gmailer
Author: Shannon Chan
Author-email: channeng@hotmail.com
License: MIT
Keywords: gmail,reports,email,email tables,analytics,report,BI,Business Intelligence
Platform: UNKNOWN
Classifier: Development Status :: 3 - Alpha
Classifier: Intended Audience :: Developers
Classifier: Intended Audience :: Information Technology
Classifier: Intended Audience :: End Users/Desktop
Classifier: Intended Audience :: Financial and Insurance Industry
Classifier: Intended Audience :: Other Audience
Classifier: Topic :: Software Development :: Build Tools
Classifier: License :: OSI Approved :: MIT License
Classifier: Natural Language :: English
Classifier: Programming Language :: Python :: 2.7
Classifier: Topic :: Communications :: Email
Classifier: Topic :: Utilities
